Metadata-Version: 2.1
Name: auto-codebase-documenter
Version: 1.2
Summary: Automatic codebase documentation tool using OpenAI GPT models
Home-page: https://github.com/abryant710/auto-codebase-documenter
Author: Alex Bryant
Author-email: alexbryant710@gmail.com
License: MIT
Platform: any
Classifier: Programming Language :: Python :: 3
Classifier: License :: OSI Approved :: MIT License
Classifier: Operating System :: OS Independent
License-File: LICENSE
